nagios/__init__.py
nagios/__main__.py
nagios/client.py
nagios/exceptions.py
nagios/rest_client.py
nagios/tests.py
nagios/utils.py
nagios/cgi/__init__.py
nagios/cgi/archive_json.py
nagios/cgi/base.py
nagios/cgi/object_json.py
nagios/cgi/status_json.py
nagios_core_api-0.2.1.dist-info/LICENSE
nagios_core_api-0.2.1.dist-info/METADATA
nagios_core_api-0.2.1.dist-info/WHEEL
nagios_core_api-0.2.1.dist-info/top_level.txt
nagios_core_api-0.2.1.dist-info/RECORD
