Metadata-Version: 2.1
Name: nagios-core-api
Version: 0.2.1
Summary: A python wrapper for querying nagios core monitoring
Home-page: https://github.com/sajalshres/nagios-core-api
Author: Sajal Shrestha
Author-email: sajal.shres@gmail.com
License: MIT
Keywords: nagios,api,rest,wrapper
Platform: UNKNOWN
Classifier: Development Status :: 3 - Alpha
Classifier: Intended Audience :: Developers
Classifier: Topic :: Software Development :: Build Tools
Classifier: License :: OSI Approved :: MIT License
Classifier: Programming Language :: Python :: 3
Classifier: Programming Language :: Python :: 3.4
Classifier: Programming Language :: Python :: 3.5
Classifier: Programming Language :: Python :: 3.6
Classifier: Programming Language :: Python :: 3.7
Classifier: Programming Language :: Python :: 3.8
Classifier: Operating System :: OS Independent
License-File: LICENSE
Requires-Dist: requests
